exo_mentions/__init__.py
exo_mentions/exceptions.py
exo_mentions/registry.py
exo_mentions/wrapper.py
exo_mentions/api/__init__.py
exo_mentions/api/serializers.py
exo_mentions/api/urls.py
exo_mentions/api/views.py
exo_mentions/mixins/__init__.py
exo_mentions/mixins/mentions_test_mixins.py
exo_mentions/signals/__init__.py
exo_mentions/signals/save_signals.py
django_exo_mentions-1.1.3.dist-info/AUTHORS.rst
django_exo_mentions-1.1.3.dist-info/LICENSE
django_exo_mentions-1.1.3.dist-info/METADATA
django_exo_mentions-1.1.3.dist-info/WHEEL
django_exo_mentions-1.1.3.dist-info/top_level.txt
django_exo_mentions-1.1.3.dist-info/RECORD
