Metadata-Version: 2.1
Name: django-exo-mentions
Version: 1.1.3
Summary: Add mention feature to your django application.
Home-page: https://github.com/exolever/django-exo-mentions
Author: Jose M. Marfil, Tomás Garzón, Javier Sújar
Author-email: josemarfyl@gmail.com, tomasgarzonhervas@gmail.com, javier.sujar@gmail.com
License: MIT
Keywords: django-exo-mentions
Platform: UNKNOWN
Classifier: Development Status :: 3 - Alpha
Classifier: Framework :: Django :: 1.11
Classifier: Framework :: Django :: 2.0
Classifier: Intended Audience :: Developers
Classifier: License :: OSI Approved :: BSD License
Classifier: Natural Language :: English
Classifier: Programming Language :: Python :: 2
Classifier: Programming Language :: Python :: 2.7
Classifier: Programming Language :: Python :: 3
Classifier: Programming Language :: Python :: 3.4
Classifier: Programming Language :: Python :: 3.5
Classifier: Programming Language :: Python :: 3.6
Requires-Dist: djangorestframework (>=3.9.1)
